streamlit_concurrency/__init__.py
streamlit_concurrency/_decorator_async.py
streamlit_concurrency/_decorator_async_test.py
streamlit_concurrency/_decorator_sync.py
streamlit_concurrency/_decorator_sync_test.py
streamlit_concurrency/_errors.py
streamlit_concurrency/_executors.py
streamlit_concurrency/_func_cache.py
streamlit_concurrency/_func_util.py
streamlit_concurrency/_func_util_test.py
streamlit_concurrency/_streamlit_hack.py
streamlit_concurrency/_streamlit_util.py
streamlit_concurrency/conftest.py
streamlit_concurrency/func_decorator.py
streamlit_concurrency/func_decorator_test.py
streamlit_concurrency/log_sink.py
streamlit_concurrency/log_sink_test.py
streamlit_concurrency/signal.py
streamlit_concurrency/state.py
streamlit_concurrency/state_test.py
streamlit_concurrency/_obsolete/decorators.py
streamlit_concurrency/demo/__init__.py
streamlit_concurrency/demo/bootstrap.py
streamlit_concurrency/demo/example_func.py
streamlit_concurrency/demo/logger_sink_viewer.py
streamlit_concurrency/demo/page_src.py
streamlit_concurrency-0.1.1.dist-info/licenses/LICENSE
streamlit_concurrency-0.1.1.dist-info/METADATA
streamlit_concurrency-0.1.1.dist-info/WHEEL
streamlit_concurrency-0.1.1.dist-info/top_level.txt
streamlit_concurrency-0.1.1.dist-info/RECORD
