Metadata-Version: 2.4
Name: streamlit-concurrency
Version: 0.1.1
Summary: Easier and safer concurrency for Streamlit
Author-email: Wang Guan <momocraft@gmail.com>
License: Apache 2.0
Requires-Python: >=3.12
License-File: LICENSE
Dynamic: license-file
